polidoro_pipeline-0.1.dist-info/licenses/LICENSE
ppipeline/__init__.py
ppipeline/pipeline.py
polidoro_pipeline-0.1.dist-info/METADATA
polidoro_pipeline-0.1.dist-info/WHEEL
polidoro_pipeline-0.1.dist-info/top_level.txt
polidoro_pipeline-0.1.dist-info/RECORD
