Metadata-Version: 2.4
Name: polidoro_pipeline
Version: 0.1
Summary: A powerful Python library for parallel data processing through a sequence of steps.
Author: Heitor Luis Polidoro
License: MIT
Project-URL: Homepage, https://github.com/heitorpolidoro/polidoro_pipeline
Classifier: Programming Language :: Python :: 3
Classifier: License :: OSI Approved :: MIT License
Classifier: Operating System :: OS Independent
Requires-Python: >=3.9
License-File: LICENSE
Dynamic: license-file
